opsmatcal/__init__.py
opsmatcal/matcalibrate.py
opsmatcal-1.2.dist-info/METADATA
opsmatcal-1.2.dist-info/WHEEL
opsmatcal-1.2.dist-info/licenses/LICENSE
opsmatcal-1.2.dist-info/RECORD
