Metadata-Version: 2.1
Name: opsmatcal
Version: 1.2
Summary: A python package for calibrating opensees uniaxial materials using genetic algorithm
Author-email: Oktay Alizadeh Arasi <ok.programss@gmail.com>
License-File: LICENSE
Classifier: License :: OSI Approved :: MIT License
Classifier: Operating System :: Microsoft :: Windows
Classifier: Programming Language :: Python :: 3
Requires-Python: >=3.9
